src/__init__.py
src/config.py
src/main.py
src/messaging/__init__.py
src/messaging/inbound.py
src/messaging/outbound.py
src/solver/__init__.py
src/solver/tsp_solver.py
src/utils/__init__.py
src/utils/distance.py
tests/__init__.py
tests/test_distance.py
tests/test_inbound.py
tests/test_outbound.py
tests/test_tsp_solver.py
tsp_planner-0.2.dist-info/METADATA
tsp_planner-0.2.dist-info/WHEEL
tsp_planner-0.2.dist-info/entry_points.txt
tsp_planner-0.2.dist-info/top_level.txt
tsp_planner-0.2.dist-info/RECORD
